pdf_oxide/__init__.py
pdf_oxide/__init__.pyi
pdf_oxide/pdf_oxide.abi3.so
pdf_oxide-0.3.1.dist-info/METADATA
pdf_oxide-0.3.1.dist-info/WHEEL
pdf_oxide-0.3.1.dist-info/licenses/LICENSE-APACHE
pdf_oxide-0.3.1.dist-info/licenses/LICENSE-MIT
pdf_oxide-0.3.1.dist-info/RECORD
