Metadata-Version: 2.4
Name: pdf_oxide
Version: 0.3.1
Classifier: Development Status :: 3 - Alpha
Classifier: Intended Audience :: Developers
Classifier: License :: OSI Approved :: MIT License
Classifier: License :: OSI Approved :: Apache Software License
Classifier: Programming Language :: Python :: 3
Classifier: Programming Language :: Python :: 3.8
Classifier: Programming Language :: Python :: 3.9
Classifier: Programming Language :: Python :: 3.10
Classifier: Programming Language :: Python :: 3.11
Classifier: Programming Language :: Python :: 3.12
Classifier: Programming Language :: Python :: 3.13
Classifier: Programming Language :: Rust
Classifier: Topic :: Software Development :: Libraries :: Python Modules
Classifier: Topic :: Text Processing :: Markup :: HTML
Classifier: Topic :: Text Processing :: Markup :: Markdown
Requires-Dist: pytest>=7.0.0 ; extra == 'test'
Requires-Dist: pytest-cov>=4.0.0 ; extra == 'test'
Provides-Extra: test
License-File: LICENSE-APACHE
License-File: LICENSE-MIT
Summary: The Complete PDF Toolkit: extract, create, and edit PDFs with one library. Rust core with Python bindings.
Keywords: pdf,text-extraction,ocr,rag,llm,markdown,document-parser
Home-Page: https://github.com/yfedoseev/pdf_oxide
Author-email: PDF Oxide Contributors <yf@yfedoseev.com>
License: MIT OR Apache-2.0
Requires-Python: >=3.8
Project-URL: Bug Tracker, https://github.com/yfedoseev/pdf_oxide/issues
Project-URL: Documentation, https://docs.rs/pdf_oxide
Project-URL: Homepage, https://github.com/yfedoseev/pdf_oxide
Project-URL: Repository, https://github.com/yfedoseev/pdf_oxide
